{"metadata":{"result_type":"recent","iso_language_code":"en"},"in_reply_to_status_id_str":null,"in_reply_to_status_id":null,"coordinates":null,"created_at":"Thu Mar 05 23:48:44 +0000 2015","truncated":false,"in_reply_to_user_id_str":null,"source":"<a href=\"http://twitter.com/download/iphone\" rel=\"nofollow\">Twitter for iPhone<\/a>","retweeted_status":{"metadata":{"result_type":"recent","iso_language_code":"en"},"in_reply_to_status_id_str":null,"in_reply_to_status_id":null,"coordinates":null,"created_at":"Thu Mar 05 23:10:39 +0000 2015","truncated":false,"in_reply_to_user_id_str":null,"source":"<a href=\"http://twitter.com\" rel=\"nofollow\">Twitter Web Client<\/a>","retweet_count":4,"retweeted":false,"geo":null,"in_reply_to_screen_name":null,"entities":{"urls":[],"hashtags":[{"indices":[6,13],"text":"nodejs"},{"indices":[21,28],"text":"xquery"},{"indices":[34,39],"text":"json"},{"indices":[43,53],"text":"MarkLogic"}],"user_mentions":[],"symbols":[]},"id_str":"573621675603820545","in_reply_to_user_id":null,"favorite_count":8,"id":573621675603820545,"text":"Using #nodejs to run #xquery over #json in #MarkLogic is really awesome!  Oh, the things I will do with this ...","place":null,"contributors":null,"lang":"en","user":{"utc_offset":null,"friends_count":113,"profile_image_url_https":"https://pbs.twimg.com/profile_images/462712136565669888/Iz-BiF0W_normal.png","listed_count":28,"profile_background_image_url":"http://pbs.twimg.com/profile_background_images/772612372/6e05a48d548fcc6a2ebda6658d7ea447.jpeg","default_profile_image":false,"favourites_count":12,"description":"Web Geek, Mathematician, open data nut, postdoc @ School of Information, UC Berkeley, PhD from University of Edinburgh School of Informatics, life is good \u2026","created_at":"Sat Mar 26 08:58:35 +0000 2011","is_translator":false,"profile_background_image_url_https":"https://pbs.twimg.com/profile_background_images/772612372/6e05a48d548fcc6a2ebda6658d7ea447.jpeg","protected":false,"screen_name":"alexmilowski","id_str":"272333682","profile_link_color":"CC6600","is_translation_enabled":false,"id":272333682,"geo_enabled":false,"profile_background_color":"020812","lang":"en","profile_sidebar_border_color":"2280A9","profile_location":null,"profile_text_color":"2280A9","verified":false,"profile_image_url":"http://pbs.twimg.com/profile_images/462712136565669888/Iz-BiF0W_normal.png","time_zone":null,"url":"http://t.co/1HEMcfGdeP","contributors_enabled":false,"profile_background_tile":false,"profile_banner_url":"https://pbs.twimg.com/profile_banners/272333682/1359085292","entities":{"description":{"urls":[]},"url":{"urls":[{"display_url":"milowski.com","indices":[0,22],"expanded_url":"http://www.milowski.com/","url":"http://t.co/1HEMcfGdeP"}]}},"statuses_count":1638,"follow_request_sent":false,"followers_count":303,"profile_use_background_image":true,"default_profile":false,"following":false,"name":"Alex Miłowski","location":"San Francisco, CA USA","profile_sidebar_fill_color":"020812","notifications":false},"favorited":false},"retweet_count":4,"retweeted":false,"geo":null,"in_reply_to_screen_name":null,"entities":{"urls":[],"hashtags":[{"indices":[24,31],"text":"nodejs"},{"indices":[39,46],"text":"xquery"},{"indices":[52,57],"text":"json"},{"indices":[61,71],"text":"MarkLogic"}],"user_mentions":[{"indices":[3,16],"screen_name":"alexmilowski","id_str":"272333682","name":"Alex Miłowski","id":272333682}],"symbols":[]},"id_str":"573631258779086848","in_reply_to_user_id":null,"favorite_count":0,"id":573631258779086848,"text":"RT @alexmilowski: Using #nodejs to run #xquery over #json in #MarkLogic is really awesome!  Oh, the things I will do with this ...","place":null,"contributors":null,"lang":"en","user":{"utc_offset":3600,"friends_count":163,"profile_image_url_https":"https://pbs.twimg.com/profile_images/470227790789230592/g0DlrMGk_normal.jpeg","listed_count":7,"profile_background_image_url":"http://abs.twimg.com/images/themes/theme1/bg.png","default_profile_image":false,"favourites_count":7,"description":"Senior Sales Engineer at MarkLogic Corporation","created_at":"Sun Feb 24 00:30:14 +0000 2008","is_translator":false,"profile_background_image_url_https":"https://abs.twimg.com/images/themes/theme1/bg.png","protected":false,"screen_name":"mehdii","id_str":"13884242","profile_link_color":"3B94D9","is_translation_enabled":false,"id":13884242,"geo_enabled":true,"profile_background_color":"000000","lang":"en","profile_sidebar_border_color":"000000","profile_location":null,"profile_text_color":"000000","verified":false,"profile_image_url":"http://pbs.twimg.com/profile_images/470227790789230592/g0DlrMGk_normal.jpeg","time_zone":"Paris","url":"http://t.co/l8QDmo9k7X","contributors_enabled":false,"profile_background_tile":false,"entities":{"description":{"urls":[]},"url":{"urls":[{"display_url":"marklogic.com","indices":[0,22],"expanded_url":"http://www.marklogic.com","url":"http://t.co/l8QDmo9k7X"}]}},"statuses_count":87,"follow_request_sent":false,"followers_count":70,"profile_use_background_image":false,"default_profile":false,"following":false,"name":"Mehdi Maachou","location":"Paris, France","profile_sidebar_fill_color":"000000","notifications":false},"favorited":false}