{"metadata":{"result_type":"recent","iso_language_code":"en"},"in_reply_to_status_id_str":null,"in_reply_to_status_id":null,"possibly_sensitive":false,"coordinates":{"coordinates":[0,0],"type":"Point"},"created_at":"Thu Mar 12 14:23:50 +0000 2015","truncated":false,"in_reply_to_user_id_str":null,"source":"<a href=\"http://twitter.com\" rel=\"nofollow\">Twitter Web Client<\/a>","retweet_count":1,"retweeted":false,"geo":{"coordinates":[0,0],"type":"Point"},"in_reply_to_screen_name":null,"entities":{"urls":[{"display_url":"computerworlduk.com/news/applicati\u2026","indices":[84,106],"expanded_url":"http://www.computerworlduk.com/news/applications/3601382/jpmorgan-consolidates-derivative-trade-systems-with-nosql-database/","url":"http://t.co/FfhDPExfsM"}],"hashtags":[{"indices":[107,123],"text":"enterprisenosql"}],"user_mentions":[],"symbols":[]},"id_str":"576025814774382593","in_reply_to_user_id":null,"favorite_count":4,"id":576025814774382593,"text":"JPMorgan modernizes and consolidates their derivatives trade systems with MarkLogic http://t.co/FfhDPExfsM #enterprisenosql","place":{"country_code":"GB","country":"United Kingdom","contained_within":[],"full_name":"City of London, London","bounding_box":{"coordinates":[[[-0.112442,51.5068],[-0.0733794,51.5068],[-0.0733794,51.522161],[-0.112442,51.522161]]],"type":"Polygon"},"place_type":"city","name":"City of London","attributes":{},"id":"3eb2c704fe8a50cb","url":"https://api.twitter.com/1.1/geo/id/3eb2c704fe8a50cb.json"},"contributors":null,"lang":"en","user":{"utc_offset":null,"friends_count":380,"profile_image_url_https":"https://pbs.twimg.com/profile_images/1811230718/john_mluc11_crop_normal.jpg","listed_count":42,"profile_background_image_url":"http://pbs.twimg.com/profile_background_images/6679262/IMG_0119.JPG","default_profile_image":false,"favourites_count":124,"description":"XQuery, XML, SPARQL, RDF, MarkLogic, Husband, Dad, Christian","created_at":"Fri Apr 18 12:24:22 +0000 2008","is_translator":false,"profile_background_image_url_https":"https://pbs.twimg.com/profile_background_images/6679262/IMG_0119.JPG","protected":false,"screen_name":"jpcs","id_str":"14432404","profile_link_color":"FF3300","is_translation_enabled":false,"id":14432404,"geo_enabled":true,"profile_background_color":"709397","lang":"en","profile_sidebar_border_color":"86A4A6","profile_location":null,"profile_text_color":"333333","verified":false,"profile_image_url":"http://pbs.twimg.com/profile_images/1811230718/john_mluc11_crop_normal.jpg","time_zone":null,"url":"http://t.co/OMZGoe0d5O","contributors_enabled":false,"profile_background_tile":true,"profile_banner_url":"https://pbs.twimg.com/profile_banners/14432404/1399656075","entities":{"description":{"urls":[]},"url":{"urls":[{"display_url":"john.snelson.org.uk","indices":[0,22],"expanded_url":"http://john.snelson.org.uk","url":"http://t.co/OMZGoe0d5O"}]}},"statuses_count":1390,"follow_request_sent":false,"followers_count":801,"profile_use_background_image":true,"default_profile":false,"following":false,"name":"John Snelson","location":"Oxford, England","profile_sidebar_fill_color":"A0C5C7","notifications":false},"favorited":false}