{"metadata":{"result_type":"recent","iso_language_code":"en"},"in_reply_to_status_id_str":null,"in_reply_to_status_id":null,"possibly_sensitive":false,"coordinates":null,"created_at":"Mon Mar 16 15:17:15 +0000 2015","truncated":false,"in_reply_to_user_id_str":null,"source":"<a href=\"https://about.twitter.com/products/tweetdeck\" rel=\"nofollow\">TweetDeck<\/a>","retweet_count":0,"retweeted":false,"geo":null,"in_reply_to_screen_name":null,"entities":{"urls":[{"display_url":"developer.marklogic.com/blog/camel-and\u2026","indices":[57,79],"expanded_url":"http://developer.marklogic.com/blog/camel-and-content-pump","url":"http://t.co/zGs6zAnMUM"}],"hashtags":[{"indices":[41,47],"text":"NoSQL"}],"user_mentions":[{"indices":[12,19],"screen_name":"Apache","id_str":"57412303","name":"Apache","id":57412303},{"indices":[30,40],"screen_name":"MarkLogic","id_str":"18295289","name":"MarkLogic","id":18295289}],"symbols":[]},"id_str":"577488805164351488","in_reply_to_user_id":null,"favorite_count":0,"id":577488805164351488,"text":"Integrating @Apache Camel and @MarkLogic #NoSQL database http://t.co/zGs6zAnMUM","place":null,"contributors":null,"lang":"en","user":{"utc_offset":3600,"friends_count":196,"profile_image_url_https":"https://pbs.twimg.com/profile_images/3662992495/07adab08abc7b5c1bb07b1a022325749_normal.jpeg","listed_count":10,"profile_background_image_url":"http://abs.twimg.com/images/themes/theme13/bg.gif","default_profile_image":false,"favourites_count":6,"description":"Principal sales engineer @ MarkLogic. Supporting our customers and partners in the Benelux and the Nordics.","created_at":"Wed Apr 22 19:21:56 +0000 2009","is_translator":false,"profile_background_image_url_https":"https://abs.twimg.com/images/themes/theme13/bg.gif","protected":false,"screen_name":"michelderu","id_str":"34368016","profile_link_color":"93A644","is_translation_enabled":false,"id":34368016,"geo_enabled":true,"profile_background_color":"B2DFDA","lang":"en","profile_sidebar_border_color":"EEEEEE","profile_location":null,"profile_text_color":"333333","verified":false,"profile_image_url":"http://pbs.twimg.com/profile_images/3662992495/07adab08abc7b5c1bb07b1a022325749_normal.jpeg","time_zone":"Amsterdam","url":"http://t.co/86HHeOUI4h","contributors_enabled":false,"profile_background_tile":false,"entities":{"description":{"urls":[]},"url":{"urls":[{"display_url":"dayon.nl","indices":[0,22],"expanded_url":"http://www.dayon.nl","url":"http://t.co/86HHeOUI4h"}]}},"statuses_count":538,"follow_request_sent":false,"followers_count":149,"profile_use_background_image":true,"default_profile":false,"following":false,"name":"Michel de Ru","location":"Delft, Netherlands","profile_sidebar_fill_color":"FFFFFF","notifications":false},"favorited":false}